dagster_sqlalchemy/__init__.py
dagster_sqlalchemy/common.py
dagster_sqlalchemy/subquery_builder_experimental.py
dagster_sqlalchemy/templated.py
dagster_sqlalchemy/version.py
dagster_sqlalchemy/examples/__init__.py
dagster_sqlalchemy/examples/sql_project_example/__init__.py
dagster_sqlalchemy/examples/sql_project_example/pipelines.py
dagster_sqlalchemy/examples/sql_project_example/print_tables.py
dagster_sqlalchemy_tests/sql_project_example/__init__.py
dagster_sqlalchemy_tests/sql_project_example/test_sql_project_pipeline.py
dagster_sqlalchemy-0.3.5.dist-info/COPYING
dagster_sqlalchemy-0.3.5.dist-info/LICENSE
dagster_sqlalchemy-0.3.5.dist-info/METADATA
dagster_sqlalchemy-0.3.5.dist-info/WHEEL
dagster_sqlalchemy-0.3.5.dist-info/top_level.txt
dagster_sqlalchemy-0.3.5.dist-info/RECORD
